pyevmasm/__init__.py
pyevmasm/__main__.py
pyevmasm/evmasm.py
pyevmasm-0.2.3.dist-info/LICENSE
pyevmasm-0.2.3.dist-info/METADATA
pyevmasm-0.2.3.dist-info/WHEEL
pyevmasm-0.2.3.dist-info/entry_points.txt
pyevmasm-0.2.3.dist-info/top_level.txt
pyevmasm-0.2.3.dist-info/RECORD
